pgcore-1.5.4.dist-info/WHEEL
pgcore-1.5.4.dist-info/METADATA
pgcore-1.5.4.dist-info/top_level.txt
pgcore-1.5.4.dist-info/RECORD
pgcore.libs/libsuitesparseconfig-e4e8c4aa.so.4.4.4
pgcore.libs/libgfortran-9925d722.so.5.0.0
pgcore.libs/libopenblas-r0-11edc3fa.3.15.so
pgcore.libs/libcholmod-8f6cf142.so.3.0.6
pgcore.libs/libquadmath-9f4e45eb.so.0.0.0
pgcore.libs/libsatlas-6c1f674f.so.3.10
pgcore.libs/libcamd-28bb7d13.so.2.4.1
pgcore.libs/libccolamd-b4f1d742.so.2.9.1
pgcore.libs/libamd-a26d1aab.so.2.4.1
pgcore.libs/libboost_python310-mt-x64-f71cf08e.so.1.86.0
pgcore.libs/libgimli-3dff6f61.so
pgcore.libs/libumfpack-2e055419.so.5.7.1
pgcore.libs/libgomp-c9fef706.so.1.0.0
pgcore.libs/libcolamd-dc193ab4.so.2.9.1
pgcore/__init__.py
pgcore/libs/_pygimli_.so
